{
 "root": {
  "data": {"text": "吉祥輪制手供養儀軌"},
  "children": [{
   "data": {
    "id": "z5oo4AnDaB",
    "created": 1646297813405,
    "text": "藏文大藏經目錄"
   },
   "children": [
    {
     "data": {
      "id": "z5oo4AnDZd",
      "created": 1646297813405,
      "text": "部類"
     },
     "children": [{"data": {
      "id": "z5oo4AnDZe",
      "created": 1646297813405,
      "text": "怛特羅部",
      "resource": ["catalog"]
     }}]
    },
    {
     "data": {
      "id": "z5oo4AnDZf",
      "created": 1646297813405,
      "text": "函號"
     },
     "children": [{"data": {
      "id": "z5oo4AnDZg",
      "created": 1646297813405,
      "text": "通帙第124Sha"
     }}]
    },
    {
     "data": {
      "id": "z5oo4AnDZh",
      "created": 1646297813405,
      "text": "經碼"
     },
     "children": [{"data": {
      "id": "z5oo4AnDZi",
      "created": 1646297813405,
      "text": "No.1468"
     }}]
    },
    {
     "data": {
      "id": "z5oo4AnDZj",
      "created": 1646297813405,
      "text": "原葉碼"
     },
     "children": [{"data": {
      "id": "z5oo4AnDZk",
      "created": 1646297813405,
      "text": "48a5-49b1"
     }}]
    },
    {
     "data": {
      "id": "z5oo4AnDZl",
      "created": 1646297813405,
      "text": "藏文經名"
     },
     "children": [{"data": {
      "id": "z5oo4AnDZm",
      "created": 1646297813405,
      "text": ""
     }}]
    },
    {
     "data": {
      "id": "z5oo4AnDZn",
      "created": 1646297813405,
      "text": "藏語羅馬轉寫經名"
     },
     "children": [{"data": {
      "id": "z5oo4AnDZo",
      "created": 1646297813405,
      "text": "Dpal ḥkhor-lo sdom-paḥi lag-mchod-kyi cho-ga shes-bya-ba"
     }}]
    },
    {
     "data": {
      "id": "z5oo4AnDZp",
      "created": 1646297813405,
      "text": "中文經名"
     },
     "children": [{"data": {
      "id": "z5oo4AnDZq",
      "created": 1646297813405,
      "text": "吉祥輪制手供養儀軌",
      "resource": ["alias"]
     }}]
    },
    {
     "data": {
      "id": "z5oo4AnDZr",
      "created": 1646297813405,
      "text": "经名简体"
     },
     "children": [{"data": {
      "id": "z5oo4AnDZs",
      "created": 1646297813405,
      "text": "吉祥轮制手供养仪轨",
      "resource": ["alias"]
     }}]
    },
    {
     "data": {
      "id": "z5oo4AnDZt",
      "created": 1646297813405,
      "text": "经名简拼"
     },
     "children": [{"data": {
      "id": "z5oo4AnDZu",
      "created": 1646297813405,
      "text": "ji xiang lun zhi shou gong yang yi gui"
     }}]
    },
    {
     "data": {
      "id": "z5oo4AnDZv",
      "created": 1646297813405,
      "text": "梵文經名"
     },
     "children": [{"data": {
      "id": "z5oo4AnDZw",
      "created": 1646297813405,
      "text": "Śrīcakrasaṁvarahastapūjāvidhi-nāma",
      "resource": ["alias"]
     }}]
    },
    {
     "data": {
      "id": "z5oo4AnDZx",
      "created": 1646297813405,
      "text": "造者"
     },
     "children": [{"data": {
      "id": "z5oo4AnDZy",
      "created": 1646297813405,
      "text": "Prajñārakṣita"
     }}]
    },
    {
     "data": {
      "id": "z5oo4AnDZz",
      "created": 1646297813405,
      "text": "西藏譯師"
     },
     "children": [{"data": {
      "id": "z5oo4AnDa0",
      "created": 1646297813405,
      "text": "Blo-ldan śes-rab"
     }}]
    },
    {
     "data": {
      "id": "z5oo4AnDa1",
      "created": 1646297813405,
      "text": "印度譯師"
     },
     "children": [{"data": {
      "id": "z5oo4AnDa2",
      "created": 1646297813405,
      "text": "Sumatikīrti"
     }}]
    },
    {
     "data": {
      "id": "z5oo4AnDa3",
      "created": 1646297813405,
      "text": "校訂"
     },
     "children": [{"data": {
      "id": "z5oo4AnDa4",
      "created": 1646297813405,
      "text": ""
     }}]
    },
    {
     "data": {
      "id": "z5oo4AnDa5",
      "created": 1646297813405,
      "text": "大正藏"
     },
     "children": [{"data": {
      "id": "z5oo4AnDa6",
      "created": 1646297813405,
      "text": ""
     }}]
    },
    {
     "data": {
      "id": "z5oo4AnDa7",
      "created": 1646297813405,
      "text": "巴利藏"
     },
     "children": [{"data": {
      "id": "z5oo4AnDa8",
      "created": 1646297813405,
      "text": ""
     }}]
    },
    {
     "data": {
      "id": "z5oo4AnDa9",
      "created": 1646297813405,
      "text": "南條文雄"
     },
     "children": [{"data": {
      "id": "z5oo4AnDaA",
      "created": 1646297813405,
      "text": ""
     }}]
    }
   ]
  }]
 },
 "template": "right",
 "theme": "fresh-blue-compat",
 "version": "21.8.18",
 "metadata": {
  "id": "l0ar7mot14z",
  "searchable": ["lookup"],
  "library": ["经目对照"],
  "catalog": ["藏文大藏經目錄"]
 }
}