{
 "root": {
  "data": {"text": "達變禪師語錄"},
  "children": [{
   "data": {
    "id": "z5cYym9fbX",
    "created": 1646116901705,
    "text": "現藏錄"
   },
   "children": [
    {
     "data": {
      "id": "z5cYym8fav",
      "created": 1646116901704,
      "text": "經名"
     },
     "children": [
      {
       "data": {
        "id": "z5cYym8faw",
        "created": 1646116901704,
        "text": "中文繁体"
       },
       "children": [{"data": {
        "id": "z5cYym8fax",
        "created": 1646116901704,
        "text": "達變禪師語錄",
        "resource": ["alias"]
       }}]
      },
      {
       "data": {
        "id": "z5cYym8fay",
        "created": 1646116901704,
        "text": "中文简体"
       },
       "children": [{"data": {
        "id": "z5cYym8faz",
        "created": 1646116901704,
        "text": "达变禅师语录",
        "resource": ["alias"]
       }}]
      },
      {
       "data": {
        "id": "z5cYym8fb0",
        "created": 1646116901704,
        "text": "中文简拼"
       },
       "children": [{"data": {
        "id": "z5cYym8fb1",
        "created": 1646116901704,
        "text": "da bian shan shi yu lu"
       }}]
      }
     ]
    },
    {
     "data": {
      "id": "z5cYym8fb2",
      "created": 1646116901704,
      "text": "作／譯者"
     },
     "children": [{"data": {
      "id": "z5cYym8fb3",
      "created": 1646116901704,
      "text": "失譯",
      "resource": ["translator"]
     }}]
    },
    {
     "data": {
      "id": "z5cYym8fb4",
      "created": 1646116901704,
      "text": "卷數"
     },
     "children": [{"data": {
      "id": "z5cYym8fb5",
      "created": 1646116901704,
      "text": "1"
     }}]
    },
    {
     "data": {
      "id": "z5cYym8fb6",
      "created": 1646116901704,
      "text": "漢文大藏經各藏細目"
     },
     "children": [
      {"data": {
       "id": "z5cYym8fb7",
       "created": 1646116901704,
       "text": "【房山石經】 (未收錄)"
      }},
      {"data": {
       "id": "z5cYym8fb8",
       "created": 1646116901704,
       "text": "【開寶藏】 (未收錄)"
      }},
      {"data": {
       "id": "z5cYym8fb9",
       "created": 1646116901704,
       "text": "【崇寧藏】 (未收錄)"
      }},
      {"data": {
       "id": "z5cYym8fbA",
       "created": 1646116901704,
       "text": "【毘盧藏】 (未收錄)"
      }},
      {"data": {
       "id": "z5cYym8fbB",
       "created": 1646116901704,
       "text": "【圓覺藏】 (未收錄)"
      }},
      {"data": {
       "id": "z5cYym8fbC",
       "created": 1646116901704,
       "text": "【趙城金藏】 (未收錄)"
      }},
      {"data": {
       "id": "z5cYym8fbD",
       "created": 1646116901704,
       "text": "【資福藏】 (未收錄)"
      }},
      {"data": {
       "id": "z5cYym8fbE",
       "created": 1646116901704,
       "text": "【磧砂藏】 (未收錄)"
      }},
      {"data": {
       "id": "z5cYym8fbF",
       "created": 1646116901704,
       "text": "【宋藏遺珍】 (未收錄)"
      }},
      {"data": {
       "id": "z5cYym8fbG",
       "created": 1646116901704,
       "text": "【高麗藏】 (未收錄)"
      }},
      {"data": {
       "id": "z5cYym8fbH",
       "created": 1646116901704,
       "text": "【普寧藏】 (未收錄)"
      }},
      {"data": {
       "id": "z5cYym8fbI",
       "created": 1646116901704,
       "text": "【至元錄】 (未收錄)"
      }},
      {"data": {
       "id": "z5cYym8fbJ",
       "created": 1646116901704,
       "text": "【洪武南藏】 (未收錄)"
      }},
      {"data": {
       "id": "z5cYym8fbK",
       "created": 1646116901704,
       "text": "【永樂南藏】 (未收錄)"
      }},
      {"data": {
       "id": "z5cYym8fbL",
       "created": 1646116901704,
       "text": "【永樂北藏】 (未收錄)"
      }},
      {"data": {
       "id": "z5cYym8fbM",
       "created": 1646116901704,
       "text": "【嘉興藏】No.1888《達變禪師語錄》清釋海澂編 部別：續藏 / 法寶總目錄經號：1887 千字文 / 函號：［續藏］ 87 函"
      }},
      {"data": {
       "id": "z5cYym8fbN",
       "created": 1646116901704,
       "text": "【嘉興藏新文豐版】［續藏］No.248《達變權禪師語錄》清 海澂錄 冊數：29 / 頁數：795 / 卷數：5"
      }},
      {"data": {
       "id": "z5cYym8fbO",
       "created": 1646116901704,
       "text": "【乾隆藏】 (未收錄)"
      }},
      {"data": {
       "id": "z5cYym8fbP",
       "created": 1646116901704,
       "text": "【縮刻藏】 (未收錄)"
      }},
      {"data": {
       "id": "z5cYym8fbQ",
       "created": 1646116901704,
       "text": "【卍正藏】 (未收錄)"
      }},
      {"data": {
       "id": "z5cYym8fbR",
       "created": 1646116901704,
       "text": "【大正藏】 (未收錄)"
      }},
      {"data": {
       "id": "z5cYym8fbS",
       "created": 1646116901704,
       "text": "【佛教大藏經】 (未收錄)"
      }},
      {"data": {
       "id": "z5cYym8fbT",
       "created": 1646116901704,
       "text": "【中華藏】 (未收錄)"
      }},
      {"data": {
       "id": "z5cYym8fbU",
       "created": 1646116901704,
       "text": "【新纂卍續藏】 (未收錄)"
      }},
      {"data": {
       "id": "z5cYym8fbV",
       "created": 1646116901704,
       "text": "【南條文雄編號】 (未收錄)"
      }},
      {"data": {
       "id": "z5cYym8fbW",
       "created": 1646116901704,
       "text": "【蔡運辰《二十五種藏經目錄對照考釋》編號】　卷中：391"
      }}
     ]
    }
   ]
  }]
 },
 "template": "right",
 "theme": "fresh-blue-compat",
 "version": "21.8.18",
 "metadata": {
  "id": "l07ri2bs2kz",
  "searchable": ["lookup"],
  "library": ["经目对照"],
  "catalog": ["現藏錄"]
 }
}